mongodb_solution_assurance_iam_util/__init__.py
mongodb_solution_assurance_iam_util/mongo_role_manager.py
mongodb_solution_assurance_iam_util-0.1.4.dist-info/licenses/LICENSE.md
mongodb_solution_assurance_iam_util-0.1.4.dist-info/METADATA
mongodb_solution_assurance_iam_util-0.1.4.dist-info/WHEEL
mongodb_solution_assurance_iam_util-0.1.4.dist-info/top_level.txt
mongodb_solution_assurance_iam_util-0.1.4.dist-info/RECORD
