Metadata-Version: 2.4
Name: mongodb_solution_assurance_iam_util
Version: 0.1.4
Summary: A collection of utilities focused on streamlining MongoDB security
Home-page: https://github.com/mongodb-industry-solutions/mdb-iam-util-python
Author: MongoDB Solutions Assurance Team
Author-email: solution.assurance@mongodb.com
License: Apache-2.0
Keywords: mongodb security iam role manager permissions pymongo
Classifier: Programming Language :: Python :: 3
Classifier: License :: OSI Approved :: Apache Software License
Classifier: Operating System :: OS Independent
Classifier: Topic :: Database
Classifier: Topic :: Security
Classifier: Intended Audience :: Developers
Classifier: Intended Audience :: System Administrators
Requires-Python: >=3.7
License-File: LICENSE.md
Requires-Dist: pymongo
Provides-Extra: dev
Requires-Dist: pytest>=7.0; extra == "dev"
Requires-Dist: twine>=4.0.2; extra == "dev"
Dynamic: author
Dynamic: author-email
Dynamic: classifier
Dynamic: description
Dynamic: description-content-type
Dynamic: home-page
Dynamic: keywords
Dynamic: license
Dynamic: license-file
Dynamic: provides-extra
Dynamic: requires-dist
Dynamic: requires-python
Dynamic: summary
